pywubi/__init__.py
pywubi/__version__.py
pywubi/constants.py
pywubi/core.py
pywubi/utlis.py
pywubi/wubi_dict.py
pywubi-0.0.2.dist-info/METADATA
pywubi-0.0.2.dist-info/RECORD
pywubi-0.0.2.dist-info/WHEEL
pywubi-0.0.2.dist-info/top_level.txt
